odoo/addons/l10n_fr_department_oversea/README.rst
odoo/addons/l10n_fr_department_oversea/__init__.py
odoo/addons/l10n_fr_department_oversea/__manifest__.py
odoo/addons/l10n_fr_department_oversea/post_install.py
odoo/addons/l10n_fr_department_oversea/data/res_country_department.xml
odoo/addons/l10n_fr_department_oversea/data/res_country_state.xml
odoo/addons/l10n_fr_department_oversea/tests/__init__.py
odoo/addons/l10n_fr_department_oversea/tests/test_department_oversea.py
odoo11_addon_l10n_fr_department_oversea-11.0.1.0.0.dist-info/DESCRIPTION.rst
odoo11_addon_l10n_fr_department_oversea-11.0.1.0.0.dist-info/METADATA
odoo11_addon_l10n_fr_department_oversea-11.0.1.0.0.dist-info/RECORD
odoo11_addon_l10n_fr_department_oversea-11.0.1.0.0.dist-info/WHEEL
odoo11_addon_l10n_fr_department_oversea-11.0.1.0.0.dist-info/metadata.json
odoo11_addon_l10n_fr_department_oversea-11.0.1.0.0.dist-info/top_level.txt
